{"ticker":"PSX","generated_at":"2026-03-17T07:11:06.381467+00:00","coverage":{"first_period":"2012-Q2","latest_period":"2026-FY","n_periods":68},"points":[{"period_label":"2012-Q2","period_kind":"quarterly","year":2012,"quarter":2,"source_count":1,"sources":["earnings_call"],"risk_signal":0.107453},{"period_label":"2012-Q3","period_kind":"quarterly","year":2012,"quarter":3,"source_count":1,"sources":["earnings_call"],"risk_signal":0.071921},{"period_label":"2013-Q1","period_kind":"quarterly","year":2013,"quarter":1,"source_count":1,"sources":["earnings_call"],"risk_signal":0.083546},{"period_label":"2013-Q2","period_kind":"quarterly","year":2013,"quarter":2,"source_count":1,"sources":["earnings_call"],"risk_signal":0.164372},{"period_label":"2013-Q3","period_kind":"quarterly","year":2013,"quarter":3,"source_count":1,"sources":["earnings_call"],"risk_signal":0.098504},{"period_label":"2013-FY","period_kind":"annual_filing","year":2013,"quarter":null,"source_count":2,"sources":["10-K","DEF_14A"],"risk_signal":0.022695},{"period_label":"2013-Q4","period_kind":"quarterly","year":2013,"quarter":4,"source_count":1,"sources":["earnings_call"],"risk_signal":0.16796},{"period_label":"2014-Q1","period_kind":"quarterly","year":2014,"quarter":1,"source_count":1,"sources":["earnings_call"],"risk_signal":0.09823},{"period_label":"2014-Q2","period_kind":"quarterly","year":2014,"quarter":2,"source_count":1,"sources":["earnings_call"],"risk_signal":0.106183},{"period_label":"2014-Q3","period_kind":"quarterly","year":2014,"quarter":3,"source_count":1,"sources":["earnings_call"],"risk_signal":0.08647},{"period_label":"2014-FY","period_kind":"annual_filing","year":2014,"quarter":null,"source_count":2,"sources":["10-K","DEF_14A"],"risk_signal":0.058015},{"period_label":"2014-Q4","period_kind":"quarterly","year":2014,"quarter":4,"source_count":1,"sources":["earnings_call"],"risk_signal":0.131293},{"period_label":"2015-Q1","period_kind":"quarterly","year":2015,"quarter":1,"source_count":1,"sources":["earnings_call"],"risk_signal":0.162619},{"period_label":"2015-Q2","period_kind":"quarterly","year":2015,"quarter":2,"source_count":1,"sources":["earnings_call"],"risk_signal":0.170267},{"period_label":"2015-Q3","period_kind":"quarterly","year":2015,"quarter":3,"source_count":1,"sources":["earnings_call"],"risk_signal":0.163107},{"period_label":"2015-FY","period_kind":"annual_filing","year":2015,"quarter":null,"source_count":2,"sources":["10-K","DEF_14A"],"risk_signal":0.040593},{"period_label":"2015-Q4","period_kind":"quarterly","year":2015,"quarter":4,"source_count":1,"sources":["earnings_call"],"risk_signal":0.13557},{"period_label":"2016-Q1","period_kind":"quarterly","year":2016,"quarter":1,"source_count":1,"sources":["earnings_call"],"risk_signal":0.086562},{"period_label":"2016-Q2","period_kind":"quarterly","year":2016,"quarter":2,"source_count":1,"sources":["earnings_call"],"risk_signal":0.128945},{"period_label":"2016-Q3","period_kind":"quarterly","year":2016,"quarter":3,"source_count":1,"sources":["earnings_call"],"risk_signal":0.142085},{"period_label":"2016-FY","period_kind":"annual_filing","year":2016,"quarter":null,"source_count":2,"sources":["10-K","DEF_14A"],"risk_signal":0.042335},{"period_label":"2016-Q4","period_kind":"quarterly","year":2016,"quarter":4,"source_count":1,"sources":["earnings_call"],"risk_signal":0.068358},{"period_label":"2017-Q1","period_kind":"quarterly","year":2017,"quarter":1,"source_count":1,"sources":["earnings_call"],"risk_signal":0.06198},{"period_label":"2017-Q2","period_kind":"quarterly","year":2017,"quarter":2,"source_count":1,"sources":["earnings_call"],"risk_signal":0.048601},{"period_label":"2017-Q3","period_kind":"quarterly","year":2017,"quarter":3,"source_count":1,"sources":["earnings_call"],"risk_signal":0.042968},{"period_label":"2017-FY","period_kind":"annual_filing","year":2017,"quarter":null,"source_count":2,"sources":["10-K","DEF_14A"],"risk_signal":0.066058},{"period_label":"2017-Q4","period_kind":"quarterly","year":2017,"quarter":4,"source_count":1,"sources":["earnings_call"],"risk_signal":0.17926},{"period_label":"2018-Q1","period_kind":"quarterly","year":2018,"quarter":1,"source_count":1,"sources":["earnings_call"],"risk_signal":0.213282},{"period_label":"2018-Q2","period_kind":"quarterly","year":2018,"quarter":2,"source_count":1,"sources":["earnings_call"],"risk_signal":0.169955},{"period_label":"2018-Q3","period_kind":"quarterly","year":2018,"quarter":3,"source_count":1,"sources":["earnings_call"],"risk_signal":0.180198},{"period_label":"2018-FY","period_kind":"annual_filing","year":2018,"quarter":null,"source_count":2,"sources":["10-K","DEF_14A"],"risk_signal":0.18323},{"period_label":"2018-Q4","period_kind":"quarterly","year":2018,"quarter":4,"source_count":1,"sources":["earnings_call"],"risk_signal":0.120527},{"period_label":"2019-Q1","period_kind":"quarterly","year":2019,"quarter":1,"source_count":1,"sources":["earnings_call"],"risk_signal":0.064228},{"period_label":"2019-Q2","period_kind":"quarterly","year":2019,"quarter":2,"source_count":1,"sources":["earnings_call"],"risk_signal":0.054662},{"period_label":"2019-Q3","period_kind":"quarterly","year":2019,"quarter":3,"source_count":1,"sources":["earnings_call"],"risk_signal":0.169347},{"period_label":"2019-FY","period_kind":"annual_filing","year":2019,"quarter":null,"source_count":2,"sources":["10-K","DEF_14A"],"risk_signal":0.031828},{"period_label":"2019-Q4","period_kind":"quarterly","year":2019,"quarter":4,"source_count":1,"sources":["earnings_call"],"risk_signal":0.060083},{"period_label":"2020-Q1","period_kind":"quarterly","year":2020,"quarter":1,"source_count":1,"sources":["earnings_call"],"risk_signal":0.082109},{"period_label":"2020-Q2","period_kind":"quarterly","year":2020,"quarter":2,"source_count":1,"sources":["earnings_call"],"risk_signal":0.096865},{"period_label":"2020-Q3","period_kind":"quarterly","year":2020,"quarter":3,"source_count":1,"sources":["earnings_call"],"risk_signal":0.058063},{"period_label":"2020-FY","period_kind":"annual_filing","year":2020,"quarter":null,"source_count":2,"sources":["10-K","DEF_14A"],"risk_signal":0.076385},{"period_label":"2020-Q4","period_kind":"quarterly","year":2020,"quarter":4,"source_count":1,"sources":["earnings_call"],"risk_signal":0.047188},{"period_label":"2021-Q1","period_kind":"quarterly","year":2021,"quarter":1,"source_count":1,"sources":["earnings_call"],"risk_signal":0.046186},{"period_label":"2021-Q2","period_kind":"quarterly","year":2021,"quarter":2,"source_count":1,"sources":["earnings_call"],"risk_signal":0.058211},{"period_label":"2021-Q3","period_kind":"quarterly","year":2021,"quarter":3,"source_count":1,"sources":["earnings_call"],"risk_signal":0.075726},{"period_label":"2021-FY","period_kind":"annual_filing","year":2021,"quarter":null,"source_count":2,"sources":["10-K","DEF_14A"],"risk_signal":0.696037},{"period_label":"2021-Q4","period_kind":"quarterly","year":2021,"quarter":4,"source_count":1,"sources":["earnings_call"],"risk_signal":0.187452},{"period_label":"2022-Q1","period_kind":"quarterly","year":2022,"quarter":1,"source_count":1,"sources":["earnings_call"],"risk_signal":0.197713},{"period_label":"2022-Q2","period_kind":"quarterly","year":2022,"quarter":2,"source_count":1,"sources":["earnings_call"],"risk_signal":0.162354},{"period_label":"2022-Q3","period_kind":"quarterly","year":2022,"quarter":3,"source_count":1,"sources":["earnings_call"],"risk_signal":0.087351},{"period_label":"2022-FY","period_kind":"annual_filing","year":2022,"quarter":null,"source_count":2,"sources":["10-K","DEF_14A"],"risk_signal":0.09143},{"period_label":"2022-Q4","period_kind":"quarterly","year":2022,"quarter":4,"source_count":1,"sources":["earnings_call"],"risk_signal":0.135038},{"period_label":"2023-Q1","period_kind":"quarterly","year":2023,"quarter":1,"source_count":1,"sources":["earnings_call"],"risk_signal":0.071203},{"period_label":"2023-Q2","period_kind":"quarterly","year":2023,"quarter":2,"source_count":1,"sources":["earnings_call"],"risk_signal":0.07777},{"period_label":"2023-Q3","period_kind":"quarterly","year":2023,"quarter":3,"source_count":1,"sources":["earnings_call"],"risk_signal":0.124873},{"period_label":"2023-FY","period_kind":"annual_filing","year":2023,"quarter":null,"source_count":2,"sources":["10-K","DEF_14A"],"risk_signal":0.132361},{"period_label":"2023-Q4","period_kind":"quarterly","year":2023,"quarter":4,"source_count":1,"sources":["earnings_call"],"risk_signal":0.094177},{"period_label":"2024-Q1","period_kind":"quarterly","year":2024,"quarter":1,"source_count":1,"sources":["earnings_call"],"risk_signal":0.043548},{"period_label":"2024-Q2","period_kind":"quarterly","year":2024,"quarter":2,"source_count":1,"sources":["earnings_call"],"risk_signal":0.084318},{"period_label":"2024-Q3","period_kind":"quarterly","year":2024,"quarter":3,"source_count":1,"sources":["earnings_call"],"risk_signal":0.060556},{"period_label":"2024-FY","period_kind":"annual_filing","year":2024,"quarter":null,"source_count":2,"sources":["10-K","DEF_14A"],"risk_signal":0.231644},{"period_label":"2024-Q4","period_kind":"quarterly","year":2024,"quarter":4,"source_count":1,"sources":["earnings_call"],"risk_signal":0.037414},{"period_label":"2025-Q1","period_kind":"quarterly","year":2025,"quarter":1,"source_count":1,"sources":["earnings_call"],"risk_signal":0.062227},{"period_label":"2025-Q2","period_kind":"quarterly","year":2025,"quarter":2,"source_count":1,"sources":["earnings_call"],"risk_signal":0.079606},{"period_label":"2025-Q3","period_kind":"quarterly","year":2025,"quarter":3,"source_count":1,"sources":["earnings_call"],"risk_signal":0.04024},{"period_label":"2025-FY","period_kind":"annual_filing","year":2025,"quarter":null,"source_count":1,"sources":["10-K"],"risk_signal":0.123957},{"period_label":"2025-Q4","period_kind":"quarterly","year":2025,"quarter":4,"source_count":1,"sources":["earnings_call"],"risk_signal":0.078815},{"period_label":"2026-FY","period_kind":"annual_filing","year":2026,"quarter":null,"source_count":1,"sources":["10-K"],"risk_signal":0.127035}]}