{"ticker":"UNP","generated_at":"2026-03-17T07:11:10.012278+00:00","coverage":{"first_period":"2004-FY","latest_period":"2026-FY","n_periods":95},"points":[{"period_label":"2004-FY","period_kind":"annual_filing","year":2004,"quarter":null,"source_count":1,"sources":["10-K"],"risk_signal":0.629189},{"period_label":"2005-FY","period_kind":"annual_filing","year":2005,"quarter":null,"source_count":2,"sources":["10-K","DEF_14A"],"risk_signal":0.555313},{"period_label":"2006-FY","period_kind":"annual_filing","year":2006,"quarter":null,"source_count":2,"sources":["10-K","DEF_14A"],"risk_signal":0.483582},{"period_label":"2007-FY","period_kind":"annual_filing","year":2007,"quarter":null,"source_count":2,"sources":["10-K","DEF_14A"],"risk_signal":0.454993},{"period_label":"2008-Q1","period_kind":"quarterly","year":2008,"quarter":1,"source_count":1,"sources":["earnings_call"],"risk_signal":0.806856},{"period_label":"2008-Q2","period_kind":"quarterly","year":2008,"quarter":2,"source_count":1,"sources":["earnings_call"],"risk_signal":0.49165},{"period_label":"2008-Q3","period_kind":"quarterly","year":2008,"quarter":3,"source_count":1,"sources":["earnings_call"],"risk_signal":0.774836},{"period_label":"2008-FY","period_kind":"annual_filing","year":2008,"quarter":null,"source_count":2,"sources":["10-K","DEF_14A"],"risk_signal":0.442648},{"period_label":"2008-Q4","period_kind":"quarterly","year":2008,"quarter":4,"source_count":1,"sources":["earnings_call"],"risk_signal":0.733657},{"period_label":"2009-Q1","period_kind":"quarterly","year":2009,"quarter":1,"source_count":1,"sources":["earnings_call"],"risk_signal":0.78225},{"period_label":"2009-Q2","period_kind":"quarterly","year":2009,"quarter":2,"source_count":1,"sources":["earnings_call"],"risk_signal":0.693694},{"period_label":"2009-Q3","period_kind":"quarterly","year":2009,"quarter":3,"source_count":1,"sources":["earnings_call"],"risk_signal":0.623377},{"period_label":"2009-FY","period_kind":"annual_filing","year":2009,"quarter":null,"source_count":2,"sources":["10-K","DEF_14A"],"risk_signal":0.438987},{"period_label":"2009-Q4","period_kind":"quarterly","year":2009,"quarter":4,"source_count":1,"sources":["earnings_call"],"risk_signal":0.632114},{"period_label":"2010-Q1","period_kind":"quarterly","year":2010,"quarter":1,"source_count":1,"sources":["earnings_call"],"risk_signal":0.736682},{"period_label":"2010-Q2","period_kind":"quarterly","year":2010,"quarter":2,"source_count":1,"sources":["earnings_call"],"risk_signal":0.730656},{"period_label":"2010-Q3","period_kind":"quarterly","year":2010,"quarter":3,"source_count":1,"sources":["earnings_call"],"risk_signal":0.760736},{"period_label":"2010-FY","period_kind":"annual_filing","year":2010,"quarter":null,"source_count":2,"sources":["10-K","DEF_14A"],"risk_signal":0.384939},{"period_label":"2010-Q4","period_kind":"quarterly","year":2010,"quarter":4,"source_count":1,"sources":["earnings_call"],"risk_signal":0.667799},{"period_label":"2011-Q1","period_kind":"quarterly","year":2011,"quarter":1,"source_count":1,"sources":["earnings_call"],"risk_signal":0.803703},{"period_label":"2011-Q2","period_kind":"quarterly","year":2011,"quarter":2,"source_count":1,"sources":["earnings_call"],"risk_signal":0.716978},{"period_label":"2011-Q3","period_kind":"quarterly","year":2011,"quarter":3,"source_count":1,"sources":["earnings_call"],"risk_signal":0.620301},{"period_label":"2011-FY","period_kind":"annual_filing","year":2011,"quarter":null,"source_count":2,"sources":["10-K","DEF_14A"],"risk_signal":0.438478},{"period_label":"2011-Q4","period_kind":"quarterly","year":2011,"quarter":4,"source_count":1,"sources":["earnings_call"],"risk_signal":0.573988},{"period_label":"2012-Q1","period_kind":"quarterly","year":2012,"quarter":1,"source_count":1,"sources":["earnings_call"],"risk_signal":0.575997},{"period_label":"2012-Q2","period_kind":"quarterly","year":2012,"quarter":2,"source_count":1,"sources":["earnings_call"],"risk_signal":0.559375},{"period_label":"2012-Q3","period_kind":"quarterly","year":2012,"quarter":3,"source_count":1,"sources":["earnings_call"],"risk_signal":0.580056},{"period_label":"2012-FY","period_kind":"annual_filing","year":2012,"quarter":null,"source_count":2,"sources":["10-K","DEF_14A"],"risk_signal":0.518414},{"period_label":"2012-Q4","period_kind":"quarterly","year":2012,"quarter":4,"source_count":1,"sources":["earnings_call"],"risk_signal":0.626047},{"period_label":"2013-Q1","period_kind":"quarterly","year":2013,"quarter":1,"source_count":1,"sources":["earnings_call"],"risk_signal":0.392232},{"period_label":"2013-Q2","period_kind":"quarterly","year":2013,"quarter":2,"source_count":1,"sources":["earnings_call"],"risk_signal":0.62076},{"period_label":"2013-Q3","period_kind":"quarterly","year":2013,"quarter":3,"source_count":1,"sources":["earnings_call"],"risk_signal":0.654516},{"period_label":"2013-FY","period_kind":"annual_filing","year":2013,"quarter":null,"source_count":2,"sources":["10-K","DEF_14A"],"risk_signal":0.445408},{"period_label":"2013-Q4","period_kind":"quarterly","year":2013,"quarter":4,"source_count":1,"sources":["earnings_call"],"risk_signal":0.653037},{"period_label":"2014-Q1","period_kind":"quarterly","year":2014,"quarter":1,"source_count":1,"sources":["earnings_call"],"risk_signal":0.748001},{"period_label":"2014-Q2","period_kind":"quarterly","year":2014,"quarter":2,"source_count":1,"sources":["earnings_call"],"risk_signal":0.714783},{"period_label":"2014-Q3","period_kind":"quarterly","year":2014,"quarter":3,"source_count":1,"sources":["earnings_call"],"risk_signal":0.771169},{"period_label":"2014-FY","period_kind":"annual_filing","year":2014,"quarter":null,"source_count":2,"sources":["10-K","DEF_14A"],"risk_signal":0.466609},{"period_label":"2014-Q4","period_kind":"quarterly","year":2014,"quarter":4,"source_count":1,"sources":["earnings_call"],"risk_signal":0.64457},{"period_label":"2015-Q1","period_kind":"quarterly","year":2015,"quarter":1,"source_count":1,"sources":["earnings_call"],"risk_signal":0.699862},{"period_label":"2015-Q2","period_kind":"quarterly","year":2015,"quarter":2,"source_count":1,"sources":["earnings_call"],"risk_signal":0.647533},{"period_label":"2015-Q3","period_kind":"quarterly","year":2015,"quarter":3,"source_count":1,"sources":["earnings_call"],"risk_signal":0.786224},{"period_label":"2015-FY","period_kind":"annual_filing","year":2015,"quarter":null,"source_count":2,"sources":["10-K","DEF_14A"],"risk_signal":0.369748},{"period_label":"2015-Q4","period_kind":"quarterly","year":2015,"quarter":4,"source_count":1,"sources":["earnings_call"],"risk_signal":0.626271},{"period_label":"2016-Q1","period_kind":"quarterly","year":2016,"quarter":1,"source_count":1,"sources":["earnings_call"],"risk_signal":0.520756},{"period_label":"2016-Q2","period_kind":"quarterly","year":2016,"quarter":2,"source_count":1,"sources":["earnings_call"],"risk_signal":0.659493},{"period_label":"2016-Q3","period_kind":"quarterly","year":2016,"quarter":3,"source_count":1,"sources":["earnings_call"],"risk_signal":0.836187},{"period_label":"2016-FY","period_kind":"annual_filing","year":2016,"quarter":null,"source_count":2,"sources":["10-K","DEF_14A"],"risk_signal":0.256884},{"period_label":"2016-Q4","period_kind":"quarterly","year":2016,"quarter":4,"source_count":1,"sources":["earnings_call"],"risk_signal":0.742222},{"period_label":"2017-Q1","period_kind":"quarterly","year":2017,"quarter":1,"source_count":1,"sources":["earnings_call"],"risk_signal":0.609317},{"period_label":"2017-Q2","period_kind":"quarterly","year":2017,"quarter":2,"source_count":1,"sources":["earnings_call"],"risk_signal":0.752082},{"period_label":"2017-Q3","period_kind":"quarterly","year":2017,"quarter":3,"source_count":1,"sources":["earnings_call"],"risk_signal":0.66829},{"period_label":"2017-FY","period_kind":"annual_filing","year":2017,"quarter":null,"source_count":2,"sources":["10-K","DEF_14A"],"risk_signal":0.467956},{"period_label":"2017-Q4","period_kind":"quarterly","year":2017,"quarter":4,"source_count":1,"sources":["earnings_call"],"risk_signal":0.661473},{"period_label":"2018-Q1","period_kind":"quarterly","year":2018,"quarter":1,"source_count":1,"sources":["earnings_call"],"risk_signal":0.614677},{"period_label":"2018-Q2","period_kind":"quarterly","year":2018,"quarter":2,"source_count":1,"sources":["earnings_call"],"risk_signal":0.550174},{"period_label":"2018-Q3","period_kind":"quarterly","year":2018,"quarter":3,"source_count":1,"sources":["earnings_call"],"risk_signal":0.616848},{"period_label":"2018-FY","period_kind":"annual_filing","year":2018,"quarter":null,"source_count":2,"sources":["10-K","DEF_14A"],"risk_signal":0.574437},{"period_label":"2018-Q4","period_kind":"quarterly","year":2018,"quarter":4,"source_count":1,"sources":["earnings_call"],"risk_signal":0.829655},{"period_label":"2019-Q1","period_kind":"quarterly","year":2019,"quarter":1,"source_count":1,"sources":["earnings_call"],"risk_signal":0.814724},{"period_label":"2019-Q2","period_kind":"quarterly","year":2019,"quarter":2,"source_count":1,"sources":["earnings_call"],"risk_signal":0.793586},{"period_label":"2019-Q3","period_kind":"quarterly","year":2019,"quarter":3,"source_count":1,"sources":["earnings_call"],"risk_signal":0.847277},{"period_label":"2019-FY","period_kind":"annual_filing","year":2019,"quarter":null,"source_count":2,"sources":["10-K","DEF_14A"],"risk_signal":0.683557},{"period_label":"2019-Q4","period_kind":"quarterly","year":2019,"quarter":4,"source_count":1,"sources":["earnings_call"],"risk_signal":0.872441},{"period_label":"2020-Q1","period_kind":"quarterly","year":2020,"quarter":1,"source_count":1,"sources":["earnings_call"],"risk_signal":0.877066},{"period_label":"2020-Q2","period_kind":"quarterly","year":2020,"quarter":2,"source_count":1,"sources":["earnings_call"],"risk_signal":0.724746},{"period_label":"2020-Q3","period_kind":"quarterly","year":2020,"quarter":3,"source_count":1,"sources":["earnings_call"],"risk_signal":0.861233},{"period_label":"2020-FY","period_kind":"annual_filing","year":2020,"quarter":null,"source_count":2,"sources":["10-K","DEF_14A"],"risk_signal":0.752488},{"period_label":"2020-Q4","period_kind":"quarterly","year":2020,"quarter":4,"source_count":1,"sources":["earnings_call"],"risk_signal":0.822963},{"period_label":"2021-Q1","period_kind":"quarterly","year":2021,"quarter":1,"source_count":1,"sources":["earnings_call"],"risk_signal":0.816183},{"period_label":"2021-Q2","period_kind":"quarterly","year":2021,"quarter":2,"source_count":1,"sources":["earnings_call"],"risk_signal":0.880755},{"period_label":"2021-Q3","period_kind":"quarterly","year":2021,"quarter":3,"source_count":1,"sources":["earnings_call"],"risk_signal":0.860363},{"period_label":"2021-FY","period_kind":"annual_filing","year":2021,"quarter":null,"source_count":2,"sources":["10-K","DEF_14A"],"risk_signal":0.872416},{"period_label":"2021-Q4","period_kind":"quarterly","year":2021,"quarter":4,"source_count":1,"sources":["earnings_call"],"risk_signal":0.845916},{"period_label":"2022-Q1","period_kind":"quarterly","year":2022,"quarter":1,"source_count":1,"sources":["earnings_call"],"risk_signal":0.888868},{"period_label":"2022-Q2","period_kind":"quarterly","year":2022,"quarter":2,"source_count":1,"sources":["earnings_call"],"risk_signal":0.863275},{"period_label":"2022-Q3","period_kind":"quarterly","year":2022,"quarter":3,"source_count":1,"sources":["earnings_call"],"risk_signal":0.731901},{"period_label":"2022-FY","period_kind":"annual_filing","year":2022,"quarter":null,"source_count":2,"sources":["10-K","DEF_14A"],"risk_signal":0.908673},{"period_label":"2022-Q4","period_kind":"quarterly","year":2022,"quarter":4,"source_count":1,"sources":["earnings_call"],"risk_signal":0.866949},{"period_label":"2023-Q1","period_kind":"quarterly","year":2023,"quarter":1,"source_count":1,"sources":["earnings_call"],"risk_signal":0.663277},{"period_label":"2023-Q2","period_kind":"quarterly","year":2023,"quarter":2,"source_count":1,"sources":["earnings_call"],"risk_signal":0.780737},{"period_label":"2023-Q3","period_kind":"quarterly","year":2023,"quarter":3,"source_count":1,"sources":["earnings_call"],"risk_signal":0.911952},{"period_label":"2023-FY","period_kind":"annual_filing","year":2023,"quarter":null,"source_count":2,"sources":["10-K","DEF_14A"],"risk_signal":0.619643},{"period_label":"2023-Q4","period_kind":"quarterly","year":2023,"quarter":4,"source_count":1,"sources":["earnings_call"],"risk_signal":0.830531},{"period_label":"2024-Q1","period_kind":"quarterly","year":2024,"quarter":1,"source_count":1,"sources":["earnings_call"],"risk_signal":0.815013},{"period_label":"2024-Q2","period_kind":"quarterly","year":2024,"quarter":2,"source_count":1,"sources":["earnings_call"],"risk_signal":0.897163},{"period_label":"2024-Q3","period_kind":"quarterly","year":2024,"quarter":3,"source_count":1,"sources":["earnings_call"],"risk_signal":0.831712},{"period_label":"2024-FY","period_kind":"annual_filing","year":2024,"quarter":null,"source_count":2,"sources":["10-K","DEF_14A"],"risk_signal":0.425121},{"period_label":"2024-Q4","period_kind":"quarterly","year":2024,"quarter":4,"source_count":1,"sources":["earnings_call"],"risk_signal":0.901339},{"period_label":"2025-Q1","period_kind":"quarterly","year":2025,"quarter":1,"source_count":1,"sources":["earnings_call"],"risk_signal":0.79222},{"period_label":"2025-Q2","period_kind":"quarterly","year":2025,"quarter":2,"source_count":1,"sources":["earnings_call"],"risk_signal":0.91296},{"period_label":"2025-Q3","period_kind":"quarterly","year":2025,"quarter":3,"source_count":1,"sources":["earnings_call"],"risk_signal":0.728435},{"period_label":"2025-FY","period_kind":"annual_filing","year":2025,"quarter":null,"source_count":2,"sources":["10-K","DEF_14A"],"risk_signal":0.444098},{"period_label":"2025-Q4","period_kind":"quarterly","year":2025,"quarter":4,"source_count":1,"sources":["earnings_call"],"risk_signal":0.901184},{"period_label":"2026-FY","period_kind":"annual_filing","year":2026,"quarter":null,"source_count":1,"sources":["10-K"],"risk_signal":0.418418}]}